vigor/__init__.py
vigor/__main__.py
vigor/compose.py
vigor/utils.py
vigor/scripts/README.md
vigor/scripts/files/combine_pdf.py
vigor/scripts/files/delete_empty_media_directory.py
vigor/scripts/files/directory_explorer.py
vigor/scripts/files/image_to_pdf.py
vigor/scripts/git/author-rewrite.sh
vigor/scripts/git/git_status.py
vigor-0.2.3.dist-info/METADATA
vigor-0.2.3.dist-info/WHEEL
vigor-0.2.3.dist-info/entry_points.txt
vigor-0.2.3.dist-info/licenses/LICENSE
vigor-0.2.3.dist-info/RECORD
