Metadata-Version: 2.4
Name: vigor
Version: 0.2.3
Summary: A collection of useful Python scripts and CLI tools.
Author-email: Ryan Liu <ryanliu6@pm.me>
License: MIT
License-File: LICENSE
Classifier: Development Status :: 3 - Alpha
Classifier: Intended Audience :: Developers
Classifier: License :: OSI Approved :: MIT License
Classifier: Programming Language :: Python :: 3
Classifier: Programming Language :: Python :: 3.12
Classifier: Programming Language :: Python :: 3.13
Classifier: Programming Language :: Python :: 3.14
Requires-Python: >=3.12
Requires-Dist: click>=8.1.7
Requires-Dist: filedate>=2.0
Requires-Dist: gitpython>=3.1.14
Requires-Dist: hurry-filesize>=0.9
Requires-Dist: pillow>=11.0.0
Requires-Dist: pypdf>=5.0.1
Provides-Extra: dev
Requires-Dist: mypy>=1.14.0; extra == 'dev'
Requires-Dist: pre-commit>=4.0.0; extra == 'dev'
Requires-Dist: pytest-cov>=4.0; extra == 'dev'
Requires-Dist: pytest-mock>=3.14; extra == 'dev'
Requires-Dist: pytest>=8.0; extra == 'dev'
Requires-Dist: ruff>=0.8.0; extra == 'dev'
Requires-Dist: types-click>=7.0; extra == 'dev'
Requires-Dist: types-pillow>=10.0; extra == 'dev'
